slrtk/__init__.py
slrtk/__main__.py
slrtk/main.py
slrtk/gtk/main.py
slrtk/mltk/main.py
slrtk/mputils/main.py
slrtk-0.0.17.dist-info/METADATA
slrtk-0.0.17.dist-info/WHEEL
slrtk-0.0.17.dist-info/entry_points.txt
slrtk-0.0.17.dist-info/RECORD
