Metadata-Version: 2.4
Name: slrtk
Version: 0.0.17
Summary: Packaging for SLR tools
Author-email: Ananay Vikram Gupta <ananay@gatech.edu>, Samantha Mau <smau3@gatech.edu>
License-Expression: MIT
Classifier: Operating System :: OS Independent
Classifier: Programming Language :: Python :: 3
Requires-Python: >=3.8
Requires-Dist: docker
Requires-Dist: requests
